MicroTwisted/__init__.py
MicroTwisted/app.py
MicroTwisted/services.py
MicroTwisted/utils.py
MicroTwisted/examples/__init__.py
MicroTwisted/examples/service1/__init__.py
MicroTwisted/examples/service1/main.py
MicroTwisted/examples/service2/__init__.py
MicroTwisted/examples/service2/main.py
MicroTwisted/examples/service3/__init__.py
MicroTwisted/examples/service3/main.py
MicroTwisted/test/__init__.py
MicroTwisted/test/bash/__init__.py
MicroTwisted/test/utils/__init__.py
MicroTwisted-0.0.1.dist-info/METADATA
MicroTwisted-0.0.1.dist-info/RECORD
MicroTwisted-0.0.1.dist-info/WHEEL
MicroTwisted-0.0.1.dist-info/top_level.txt
