Metadata-Version: 2.1
Name: MicroTwisted
Version: 0.0.1
Summary: Micro Service Manager made with Twisted
Home-page: https://github.com/MaximilianoRom7/MicroTwisted
Author: Maximiliano Romay Figueroa
Author-email: maximilianorom7@gmail.com
License: UNKNOWN
Platform: UNKNOWN
Classifier: Programming Language :: Python :: 3
Classifier: Operating System :: OS Independent
